{"version": 0.6, "generator": "Overpass API 0.7.62.1 084b4234", "osm3s": {"timestamp_osm_base": "2024-06-11T13:52:15Z", "copyright": "The data included in this document is from www.openstreetmap.org. The data is made available under ODbL."}, "elements": [{"type": "node", "id": 1841368287, "lat": 51.3537985, "lon": 6.4140422}, {"type": "node", "id": 1841368798, "lat": 51.3538773, "lon": 6.4140546}, {"type": "node", "id": 1841368828, "lat": 51.3538854, "lon": 6.4139244}, {"type": "node", "id": 1841368956, "lat": 51.3539063, "lon": 6.4139919}, {"type": "node", "id": 1841368992, "lat": 51.3539126, "lon": 6.4138908}, {"type": "node", "id": 1841369005, "lat": 51.3539141, "lon": 6.4138652}, {"type": "node", "id": 1841369846, "lat": 51.3539367, "lon": 6.4139967}, {"type": "node", "id": 1841369858, "lat": 51.3539391, "lon": 6.4139581}, {"type": "node", "id": 1841369903, "lat": 51.3539445, "lon": 6.4138699}, {"type": "node", "id": 1841369919, "lat": 51.3539468, "lon": 6.4138325}, {"type": "node", "id": 1841370008, "lat": 51.3539676, "lon": 6.4139626}, {"type": "node", "id": 1841370021, "lat": 51.3539716, "lon": 6.4138988}, {"type": "node", "id": 1841370026, "lat": 51.3539726, "lon": 6.413899}, {"type": "node", "id": 1841370038, "lat": 51.3539765, "lon": 6.4138372}, {"type": "node", "id": 9323013324, "lat": 51.3538065, "lon": 6.413912}, {"type": "way", "id": 173320176, "nodes": [9323013324, 1841368828, 1841368798, 1841368287, 9323013324], "tags": {"building": "semidetached_house", "roof:shape": "gabled"}}, {"type": "way", "id": 173321094, "nodes": [1841369903, 1841369919, 1841370038, 1841370026, 1841370021, 1841370008, 1841369858, 1841369903], "tags": {"building": "yes", "description": "Parken (allgemein)", "source": "Kreis_Viersen_Katasteramt_2012_06"}}, {"type": "way", "id": 784131100, "nodes": [1841369858, 1841369846, 1841368956, 1841368992, 1841369005, 1841369903, 1841369858], "tags": {"building": "yes", "description": "Parken (allgemein)", "source": "Kreis_Viersen_Katasteramt_2012_06"}}]}